MANIFEST.in
README.rst
history.rst
setup.py
version.txt
python_simplemail.egg-info/PKG-INFO
python_simplemail.egg-info/SOURCES.txt
python_simplemail.egg-info/dependency_links.txt
python_simplemail.egg-info/top_level.txt
simplemail/__init__.py
simplemail/lgpl-3.0.txt
simplemail/mit-license.txt
simplemail/mit-lizenz-deutsch.txt