Metadata-Version: 1.1
Name: python-simplemail
Version: 2.1.0
Summary: Send Emails with Python - Simple SMTP Email Client Library
Home-page: https://github.com/gerold-penz/python-simplemail
Author: Gerold Penz
Author-email: gerold@halvar.at
License: UNKNOWN
Download-URL: https://github.com/gerold-penz/python-simplemail/raw/master/dist/python-simplemail-2.1.0.tar.gz
Keywords: Email,Send,Attachments,E-Mail,SMTP,Client,Simplemail
Platform: UNKNOWN
Classifier: Development Status :: 5 - Production/Stable
Classifier: Intended Audience :: Developers
Classifier: License :: OSI Approved :: GNU Library or Lesser General Public License (LGPL)
Classifier: License :: OSI Approved :: MIT License
Classifier: Operating System :: OS Independent
Classifier: Programming Language :: Python :: 2
Classifier: Topic :: Communications :: Email
Classifier: Topic :: Software Development :: Libraries :: Python Modules
Classifier: Topic :: System :: Networking
